pm_studio_mcp/__init__.py
pm_studio_mcp/__main__.py
pm_studio_mcp/config.py
pm_studio_mcp/server.py
pm_studio_mcp/internal_prompt/competitor_analysis.py
pm_studio_mcp/internal_prompt/data_analysis.py
pm_studio_mcp/internal_prompt/feedback_analysis.py
pm_studio_mcp/internal_prompt/mission_review.py
pm_studio_mcp/internal_prompt/pm_studio_prompt.py
pm_studio_mcp/skills/edge_mobile_dau_weekly_report/__init__.py
pm_studio_mcp/skills/edge_mobile_dau_weekly_report/contributor_analysis.py
pm_studio_mcp/skills/edge_mobile_dau_weekly_report/edge_mobile_weekly_report_utils.py
pm_studio_mcp/skills/edge_mobile_dau_weekly_report/html_report_generator.py
pm_studio_mcp/skills/edge_mobile_dau_weekly_report/weekly_report_teams_summary.py
pm_studio_mcp/tools/mobbin_crawl/analyze_single_flow.py
pm_studio_mcp/tools/mobbin_crawl/catalog.py
pm_studio_mcp/tools/mobbin_crawl/clean_single_flow_apps.py
pm_studio_mcp/tools/mobbin_crawl/index.py
pm_studio_mcp/tools/mobbin_crawl/run.py
pm_studio_mcp/tools/mobbin_crawl/seed.py
pm_studio_mcp/tools/mobbin_crawl/utils.py
pm_studio_mcp/utils/data_visualization_utils.py
pm_studio_mcp/utils/file_utils.py
pm_studio_mcp/utils/greeting.py
pm_studio_mcp/utils/matching_utils.py
pm_studio_mcp/utils/product_insights_orchestrator.py
pm_studio_mcp/utils/data_handlers/base_handler.py
pm_studio_mcp/utils/data_handlers/chrome_features_handler.py
pm_studio_mcp/utils/data_handlers/dataai_handler.py
pm_studio_mcp/utils/data_handlers/google_ads_handler.py
pm_studio_mcp/utils/data_handlers/product_insights_orchestrator.py
pm_studio_mcp/utils/data_handlers/reddit_handler.py
pm_studio_mcp/utils/data_handlers/unwrap_handler.py
pm_studio_mcp/utils/design/__init__.py
pm_studio_mcp/utils/design/dribbble_headless_browser/searcher.py
pm_studio_mcp/utils/design/dribbble_headless_browser/test_dribbble.py
pm_studio_mcp/utils/design/figma_search/__init__.py
pm_studio_mcp/utils/design/figma_search/client.py
pm_studio_mcp/utils/design/figma_search/models.py
pm_studio_mcp-0.9.5.dist-info/METADATA
pm_studio_mcp-0.9.5.dist-info/WHEEL
pm_studio_mcp-0.9.5.dist-info/entry_points.txt
pm_studio_mcp-0.9.5.dist-info/top_level.txt
pm_studio_mcp-0.9.5.dist-info/RECORD
