Metadata-Version: 2.4
Name: pm-studio-mcp
Version: 0.9.5
Summary: PM Studio MCP Server - A Model Context Protocol server for product managers
Requires-Python: >=3.10
Requires-Dist: fastmcp
Requires-Dist: matplotlib
Requires-Dist: seaborn
Requires-Dist: pandas
Requires-Dist: numpy
Requires-Dist: markdown
Requires-Dist: markitdown[docx,pdf,pptx,xls]
Requires-Dist: praw>=7.7.0
Requires-Dist: crawl4ai>=0.6.2
Requires-Dist: msal[broker]<2,>=1.33
Requires-Dist: azure-identity<2.0.0,>=1.15.0
Requires-Dist: google-auth-oauthlib>=1.2.2
Requires-Dist: google-ads>=28.0.0
Requires-Dist: pysocks>=1.7.1
Requires-Dist: plotly>=5.14.0
Requires-Dist: httpx>=0.25.0
